maxcompute_mcp_server/__init__.py
maxcompute_mcp_server/server.py
maxcompute_mcp_server-0.1.3.dist-info/METADATA
maxcompute_mcp_server-0.1.3.dist-info/WHEEL
maxcompute_mcp_server-0.1.3.dist-info/entry_points.txt
maxcompute_mcp_server-0.1.3.dist-info/licenses/LICENSE.txt
maxcompute_mcp_server-0.1.3.dist-info/RECORD
