Metadata-Version: 2.4
Name: maxcompute-mcp-server
Version: 0.1.3
Summary: A MCP server for MaxCompute
License-File: LICENSE.txt
Requires-Python: >=3.10
Requires-Dist: mcp>=1.0.0
Requires-Dist: pyodps>=0.12.2.1
